odoo/addons/base_translation_field_label/README.rst
odoo/addons/base_translation_field_label/__init__.py
odoo/addons/base_translation_field_label/__manifest__.py
odoo/addons/base_translation_field_label/i18n/base_translation_field_label.pot
odoo/addons/base_translation_field_label/models/__init__.py
odoo/addons/base_translation_field_label/models/ir_translation.py
odoo/addons/base_translation_field_label/readme/CONFIGURE.rst
odoo/addons/base_translation_field_label/readme/CONTRIBUTORS.rst
odoo/addons/base_translation_field_label/readme/DESCRIPTION.rst
odoo/addons/base_translation_field_label/static/description/icon.png
odoo/addons/base_translation_field_label/static/description/index.html
odoo/addons/base_translation_field_label/tests/__init__.py
odoo/addons/base_translation_field_label/tests/test_base_transaltion_field_label.py
odoo/addons/base_translation_field_label/views/ir_translation_views.xml
odoo_addon_base_translation_field_label-15.0.1.0.0.3.dist-info/METADATA
odoo_addon_base_translation_field_label-15.0.1.0.0.3.dist-info/WHEEL
odoo_addon_base_translation_field_label-15.0.1.0.0.3.dist-info/top_level.txt
odoo_addon_base_translation_field_label-15.0.1.0.0.3.dist-info/RECORD
